fsq-0.2.5.data/scripts/fsq
fsq-0.2.5.data/data/share/man/man1/fsq-jsonrpcd.1
fsq-0.2.5.data/data/share/man/man1/fsq-rm-host.1
fsq-0.2.5.data/data/share/man/man1/fsq-install.1
fsq-0.2.5.data/data/share/man/man1/fsq-enqueue.1
fsq-0.2.5.data/data/share/man/man1/fsq.1
fsq-0.2.5.data/data/share/man/man1/fsq-up.1
fsq-0.2.5.data/data/share/man/man1/fsq-scan.1
fsq-0.2.5.data/data/share/man/man1/fsq-push.1
fsq-0.2.5.data/data/share/man/man1/fsq-add-host.1
fsq-0.2.5.data/data/share/man/man1/fsq-up-host.1
fsq-0.2.5.data/data/share/man/man1/fsq-down.1
fsq-0.2.5.data/data/share/man/man1/fsq-down-host.1
fsq-0.2.5.data/data/share/man/man7/fsq.7
fsq-0.2.5.data/data/libexec/fsq/push.py
fsq-0.2.5.data/data/libexec/fsq/up.py
fsq-0.2.5.data/data/libexec/fsq/scan.py
fsq-0.2.5.data/data/libexec/fsq/enqueue.py
fsq-0.2.5.data/data/libexec/fsq/add-host.py
fsq-0.2.5.data/data/libexec/fsq/host-dist.py
fsq-0.2.5.data/data/libexec/fsq/up-host.py
fsq-0.2.5.data/data/libexec/fsq/jsonrpcd.py
fsq-0.2.5.data/data/libexec/fsq/install.py
fsq-0.2.5.data/data/libexec/fsq/down-host.py
fsq-0.2.5.data/data/libexec/fsq/rm-host.py
fsq-0.2.5.data/data/libexec/fsq/down.py
fsq/configure.py
fsq/push.py
fsq/done.py
fsq/__init__.py
fsq/lists.py
fsq/scan.py
fsq/exceptions.py
fsq/enqueue.py
fsq/constants.py
fsq/ratelimit.py
fsq/items.py
fsq/install.py
fsq/const.py
fsq/utility.py
fsq/internal.py
fsq/encode.py
fsq/path.py
fsq/construct.py
fsq/remote/__init__.py
fsq/remote/v1.py
fsq/tests/configure.py
fsq/tests/__init__.py
fsq/tests/scan.py
fsq/tests/FSQTestCase.py
fsq/tests/enqueue.py
fsq/tests/constants.py
fsq/tests/install.py
fsq/tests/const.py
fsq/tests/internal.py
fsq/tests/encode.py
fsq/tests/run.py
fsq/tests/path.py
fsq/tests/construct.py
fsq-0.2.5.dist-info/DESCRIPTION.rst
fsq-0.2.5.dist-info/METADATA
fsq-0.2.5.dist-info/WHEEL
fsq-0.2.5.dist-info/RECORD
fsq-0.2.5.dist-info/metadata.json
fsq-0.2.5.dist-info/top_level.txt
