Metadata-Version: 2.0
Name: fsq
Version: 0.2.5
Summary: File System Queue
Home-page: https://github.com/axialmarket/fsq
Author: Matthew Story
Author-email: matt.story@axial.net
License: 3-BSD
Platform: UNKNOWN
Requires-Dist: jsonrpclib (>=0.1.3)
